<?xml version="1.0" encoding="UTF-8" ?>
<data>
	<meshes>
		<mesh>
			<name>cube</name>
			<primitives>
				<primitive>
					<material_index>0</material_index>
					<vertices>meshes/cube/vert0.txt</vertices>
					<indices>meshes/cube/indices.txt</indices>
				</primitive>
				<primitive>
					<material_index>1</material_index>
					<vertices>meshes/cube/vert1.txt</vertices>
					<indices>meshes/cube/indices.txt</indices>
				</primitive>
				<primitive>
					<material_index>2</material_index>
					<vertices>meshes/cube/vert2.txt</vertices>
					<indices>meshes/cube/indices.txt</indices>
				</primitive>
				<primitive>
					<material_index>3</material_index>
					<vertices>meshes/cube/vert3.txt</vertices>
					<indices>meshes/cube/indices.txt</indices>
				</primitive>
				<primitive>
					<material_index>4</material_index>
					<vertices>meshes/cube/vert4.txt</vertices>
					<indices>meshes/cube/indices.txt</indices>
				</primitive>
				<primitive>
					<material_index>5</material_index>
					<vertices>meshes/cube/vert5.txt</vertices>
					<indices>meshes/cube/indices.txt</indices>
				</primitive>
			</primitives>
			<materials>
				<material>
					<x>0</x>
					<y>155</y>
					<z>72</z>
				</material>
				<material>
					<x>255</x>
					<y>255</y>
					<z>255</z>
				</material>
				<material>
					<x>183</x>
					<y>18</y>
					<z>52</z>
				</material>
				<material>
					<x>255</x>
					<y>213</y>
					<z>0</z>
				</material>
				<material>
					<x>0</x>
					<y>70</y>
					<z>173</z>
				</material>
				<material>
					<x>255</x>
					<y>88</y>
					<z>0</z>
				</material>
			</materials>
		</mesh>
	</meshes>
</data>
